napari_data_inspection/__init__.py
napari_data_inspection/_cli.py
napari_data_inspection/napari.yaml
napari_data_inspection/data_inspection/__init__.py
napari_data_inspection/data_inspection/_widget.py
napari_data_inspection/data_inspection/_widget_gui.py
napari_data_inspection/data_inspection/_widget_io.py
napari_data_inspection/data_inspection/_widget_navigation.py
napari_data_inspection/dataset_inspection/__init__.py
napari_data_inspection/dataset_inspection/dataset_widget.py
napari_data_inspection/widgets/__init__.py
napari_data_inspection/widgets/layers_block_widget.py
napari_data_inspection-1.0.3.dist-info/licenses/LICENSE
napari_data_inspection-1.0.3.dist-info/METADATA
napari_data_inspection-1.0.3.dist-info/WHEEL
napari_data_inspection-1.0.3.dist-info/entry_points.txt
napari_data_inspection-1.0.3.dist-info/top_level.txt
napari_data_inspection-1.0.3.dist-info/RECORD
