Metadata-Version: 2.4
Name: napari-data-inspection
Version: 1.0.3
Summary: Data Inspection Plugin, designed to streamline file navigation and enhance the efficiency of data inspection.
Author: Lars Krämer
Author-email: lars.kraemer@dkfz-heidelberg.de
License: 
Project-URL: Homepage, https://github.com/MIC-DKFZ/napari-data-inspection
Project-URL: Code, https://github.com/MIC-DKFZ/napari-data-inspection
Classifier: Development Status :: 2 - Pre-Alpha
Classifier: Framework :: napari
Classifier: Intended Audience :: Developers
Classifier: License :: OSI Approved :: Apache Software License
Classifier: Operating System :: OS Independent
Classifier: Programming Language :: Python
Classifier: Programming Language :: Python :: 3
Classifier: Programming Language :: Python :: 3 :: Only
Classifier: Programming Language :: Python :: 3.10
Classifier: Programming Language :: Python :: 3.11
Classifier: Programming Language :: Python :: 3.12
Classifier: Programming Language :: Python :: 3.13
Classifier: Topic :: Scientific/Engineering :: Image Processing
Requires-Python: >=3.10
License-File: LICENSE
Requires-Dist: numpy
Requires-Dist: napari
Requires-Dist: qtpy
Requires-Dist: napari_toolkit
Requires-Dist: omegaconf
Requires-Dist: vidata
Provides-Extra: all
Requires-Dist: napari[all]; extra == "all"
Provides-Extra: testing
Requires-Dist: tox; extra == "testing"
Requires-Dist: pytest; extra == "testing"
Requires-Dist: pytest-cov; extra == "testing"
Requires-Dist: pytest-qt; extra == "testing"
Requires-Dist: napari; extra == "testing"
Requires-Dist: pyqt5; extra == "testing"
Requires-Dist: omegaconf; extra == "testing"
Dynamic: license-file
